odoo10_addon_base_url-10.0.0.2.0-nspkg.pth
odoo/addons/base_url/README.rst
odoo/addons/base_url/__init__.py
odoo/addons/base_url/__manifest__.py
odoo/addons/base_url/models/__init__.py
odoo/addons/base_url/models/abstract_url.py
odoo/addons/base_url/models/url_url.py
odoo/addons/base_url/security/ir.model.access.csv
odoo/addons/base_url/tests/__init__.py
odoo/addons/base_url/tests/models.py
odoo/addons/base_url/tests/test_abstract_url.py
odoo/addons/base_url/views/url_view.xml
odoo10_addon_base_url-10.0.0.2.0.dist-info/METADATA
odoo10_addon_base_url-10.0.0.2.0.dist-info/WHEEL
odoo10_addon_base_url-10.0.0.2.0.dist-info/namespace_packages.txt
odoo10_addon_base_url-10.0.0.2.0.dist-info/top_level.txt
odoo10_addon_base_url-10.0.0.2.0.dist-info/RECORD
