Metadata-Version: 2.1
Name: odoo10-addon-base-url
Version: 10.0.0.2.0
Summary: keep history of url for products & categories
Home-page: http://www.akretion.com/fr
Author: Akretion, ACSONE SA/NV
License: AGPL-3
Platform: UNKNOWN
Classifier: Programming Language :: Python
Classifier: Framework :: Odoo
Classifier: License :: OSI Approved :: GNU Affero General Public License v3
Requires-Python: ~=2.7
Requires-Dist: odoo (<10.1dev,>=10.0)
Requires-Dist: slugify
